monorepo_loader/__init__.py
monorepo_loader/setuptools_monorepo.py
setuptools_monorepo-0.0.4.dist-info/LICENSE
setuptools_monorepo-0.0.4.dist-info/METADATA
setuptools_monorepo-0.0.4.dist-info/WHEEL
setuptools_monorepo-0.0.4.dist-info/entry_points.txt
setuptools_monorepo-0.0.4.dist-info/top_level.txt
setuptools_monorepo-0.0.4.dist-info/RECORD
